ks33requests/__init__.py
ks33requests/_scm_version.py
ks33requests/auth.py
ks33requests/client.py
ks33requests/errors.py
ks33requests/utils.py
ks33requests/schemas/__init__.py
ks33requests/schemas/s3_api.py
ks33requests/schemas/s3_sub.py
ks33requests-0.1.3.dist-info/AUTHORS.md
ks33requests-0.1.3.dist-info/METADATA
ks33requests-0.1.3.dist-info/WHEEL
ks33requests-0.1.3.dist-info/top_level.txt
ks33requests-0.1.3.dist-info/RECORD
