Metadata-Version: 2.1
Name: ks33requests
Version: 0.1.3
Summary: 适用于金山云对象存储(KS3)的简单 Python3 客户端
Home-page: https://github.com/tanbro/ks33requests
License: GNU General Public License v3 or later
Platform: UNKNOWN
Classifier: License :: OSI Approved :: GNU General Public License v3 or later (GPLv3+)
Classifier: Development Status :: 3 - Alpha
Classifier: Intended Audience :: Developers
Classifier: Natural Language :: Chinese (Simplified)
Classifier: Operating System :: OS Independent
Classifier: Programming Language :: Python
Classifier: Programming Language :: Python :: 3
Classifier: Programming Language :: Python :: 3 :: Only
Classifier: Topic :: Software Development :: Libraries :: Python Modules
Classifier: Topic :: Internet :: WWW/HTTP
Requires-Dist: requests (<3.0,>=2.0)
Requires-Dist: lxml (<5.0,>=4.0)
